qolsys_controller/__init__.py
qolsys_controller/adc_device.py
qolsys_controller/adc_service.py
qolsys_controller/adc_service_garagedoor.py
qolsys_controller/controller.py
qolsys_controller/enum.py
qolsys_controller/enum_adc.py
qolsys_controller/enum_zwave.py
qolsys_controller/errors.py
qolsys_controller/mdns.py
qolsys_controller/mqtt_command.py
qolsys_controller/mqtt_command_queue.py
qolsys_controller/observable.py
qolsys_controller/observable_v2.py
qolsys_controller/panel.py
qolsys_controller/partition.py
qolsys_controller/pki.py
qolsys_controller/scene.py
qolsys_controller/settings.py
qolsys_controller/state.py
qolsys_controller/task_manager.py
qolsys_controller/users.py
qolsys_controller/utils_mqtt.py
qolsys_controller/weather.py
qolsys_controller/zone.py
qolsys_controller/zwave_device.py
qolsys_controller/zwave_dimmer.py
qolsys_controller/zwave_energy_clamp.py
qolsys_controller/zwave_garagedoor.py
qolsys_controller/zwave_generic.py
qolsys_controller/zwave_lock.py
qolsys_controller/zwave_outlet.py
qolsys_controller/zwave_service_meter.py
qolsys_controller/zwave_service_multilevelsensor.py
qolsys_controller/zwave_thermometer.py
qolsys_controller/zwave_thermostat.py
qolsys_controller/database/db.py
qolsys_controller/database/table.py
qolsys_controller/database/table_alarmedsensor.py
qolsys_controller/database/table_automation.py
qolsys_controller/database/table_country_locale.py
qolsys_controller/database/table_dashboard_msgs.py
qolsys_controller/database/table_dimmerlight.py
qolsys_controller/database/table_doorlock.py
qolsys_controller/database/table_eu_event.py
qolsys_controller/database/table_heat_map.py
qolsys_controller/database/table_history.py
qolsys_controller/database/table_iqremotesettings.py
qolsys_controller/database/table_iqrouter_network_config.py
qolsys_controller/database/table_iqrouter_user_device.py
qolsys_controller/database/table_master_slave.py
qolsys_controller/database/table_nest_device.py
qolsys_controller/database/table_output_rules.py
qolsys_controller-0.2.7.dist-info/METADATA
qolsys_controller-0.2.7.dist-info/WHEEL
qolsys_controller-0.2.7.dist-info/licenses/LICENSE
qolsys_controller-0.2.7.dist-info/RECORD
