Metadata-Version: 2.4
Name: qolsys-controller
Version: 0.2.7
Summary: A Python module that emulates a virtual IQ Remote device, enabling full local control of a Qolsys IQ Panel
Project-URL: Homepage, https://github.com/EHylands/QolsysController
Project-URL: Issues, https://github.com/EHylands/QolsysController/issues
Project-URL: Repository, https://github.com/EHylands/QolsysController.git
Author: Eric Hylands
License-Expression: MIT
License-File: LICENSE
Classifier: License :: OSI Approved :: MIT License
Classifier: Programming Language :: Python :: 3.12
Classifier: Topic :: Home Automation
Requires-Python: >=3.12
